<?xml version="1.0" encoding="UTF-8"?>
<feature
      id="ummisco.gama.feature.audio"
      label="Audio"
      version="1.9.1.qualifier"
      provider-name="UMMISCO"
      plugin="ummisco.gaml.extensions.sound">

   <description url="http://www.example.com/description">
      Audio features for GAMA (Experimental right now)
   </description>

   <copyright url="http://www.example.com/copyright">
      [Enter Copyright Description here.]
   </copyright>

   <license url="http://www.example.com/license">
      [Enter License Description here.]
   </license>

   <url>
      <update label="GAMA 1.9.1 Update Site" url="https://updates.gama-platform.org/1.9.1"/>
   </url>

   <requires>
      <import plugin="msi.gama.core"/>
      <import plugin="msi.gama.ext"/>
   </requires>

   <plugin
         id="ummisco.gaml.extensions.sound"
         download-size="0"
         install-size="0"
         version="0.0.0"/>

</feature>
